[
  {
    "question": "Which word means to take control or possession of a place?",
    "choices": [
      "occupy",
      "uproot",
      "desertification",
      "clearance"
    ]
  },
  {
    "question": "What is the term for a curved structure or shape?",
    "choices": [
      "arc",
      "bush",
      "sterile",
      "humidity"
    ]
  },
  {
    "question": "The process of fertile land turning into desert is called:",
    "choices": [
      "desertification",
      "clearance",
      "habitat",
      "wildlife"
    ]
  },
  {
    "question": "Which word refers to the removal of trees or vegetation from an area?",
    "choices": [
      "clearance",
      "humidity",
      "irresponsible",
      "to little avail"
    ]
  },
  {
    "question": "A shrub or clump of shrubs with stems of moderate length is called a:",
    "choices": [
      "bush",
      "habitat",
      "wildlife",
      "sterile"
    ]
  },
  {
    "question": "To pull something out by the roots means to:",
    "choices": [
      "uproot",
      "escalate",
      "occupy",
      "devour"
    ]
  },
  {
    "question": "The amount of water vapor in the air is called:",
    "choices": [
      "humidity",
      "clearance",
      "sterile",
      "arc"
    ]
  },
  {
    "question": "Which word means free from bacteria or other living microorganisms?",
    "choices": [
      "sterile",
      "irresponsible",
      "to little avail",
      "wildlife"
    ]
  },
  {
    "question": "Acting without considering the consequences is considered:",
    "choices": [
      "irresponsible",
      "humidity",
      "habitat",
      "bush"
    ]
  },
  {
    "question": "The natural home or environment of an animal, plant, or other organism is called its:",
    "choices": [
      "habitat",
      "uproot",
      "occupy",
      "escalate"
    ]
  },
  {
    "question": "Which word refers to undomesticated animals living in their natural environment?",
    "choices": [
      "wildlife",
      "sterile",
      "clearance",
      "arc"
    ]
  },
  {
    "question": "The phrase \"to little avail\" means:",
    "choices": [
      "with little or no success",
      "to occupy forcefully",
      "to remove by the roots",
      "to increase rapidly"
    ]
  },
  {
    "question": "To consume or destroy something rapidly and completely is to:",
    "choices": [
      "devour",
      "uproot",
      "escalate",
      "to little avail"
    ]
  },
  {
    "question": "Which word means to increase rapidly in extent, volume, or amount?",
    "choices": [
      "escalate",
      "habitat",
      "sterile",
      "irresponsible"
    ]
  }
]
